setup.py
pipfunctionfirst/__init__.py
pipfunctionfirst.egg-info/PKG-INFO
pipfunctionfirst.egg-info/SOURCES.txt
pipfunctionfirst.egg-info/dependency_links.txt
pipfunctionfirst.egg-info/not-zip-safe
pipfunctionfirst.egg-info/top_level.txt