Metadata-Version: 1.0
Name: pipfunctionfirst
Version: 1.0
Summary: The pipfunctionfirst joke in the world
Home-page: https://github.com/zksfyz/pipfunctionfirst
Author: MagicNet
Author-email: zksfyz@gmail.com
License: MIT
Platform: UNKNOWN
